{"mean":{"confidence_interval":{"confidence_level":0.95,"lower_bound":5170698.915700002,"upper_bound":5225821.331150003},"point_estimate":5197459.482999999,"standard_error":14048.287276159877},"median":{"confidence_interval":{"confidence_level":0.95,"lower_bound":5147509.1,"upper_bound":5199307.6},"point_estimate":5184679.15,"standard_error":11830.81163049553},"median_abs_dev":{"confidence_interval":{"confidence_level":0.95,"lower_bound":77406.98940575095,"upper_bound":151867.75614380755},"point_estimate":102607.63071835028,"standard_error":18309.346469071315},"slope":null,"std_dev":{"confidence_interval":{"confidence_level":0.95,"lower_bound":112758.4432563237,"upper_bound":166775.7718275004},"point_estimate":141001.84395507647,"standard_error":13823.68092819194}}