{"mean":{"confidence_interval":{"confidence_level":0.95,"lower_bound":34508300.539875,"upper_bound":35970994.02425},"point_estimate":35210096.795,"standard_error":373190.1052346146},"median":{"confidence_interval":{"confidence_level":0.95,"lower_bound":33209802.0,"upper_bound":33621605.0},"point_estimate":33318849.0,"standard_error":98131.48347216597},"median_abs_dev":{"confidence_interval":{"confidence_level":0.95,"lower_bound":385122.39306271076,"upper_bound":1058190.905213356},"point_estimate":632514.5844206214,"standard_error":164468.62725805328},"slope":null,"std_dev":{"confidence_interval":{"confidence_level":0.95,"lower_bound":2942454.197211282,"upper_bound":4408932.244227341},"point_estimate":3749605.7874600748,"standard_error":375125.5200270682}}